LingzuWenkuFix1/README.md
LingzuWenkuFix1/__init__.py
LingzuWenkuFix1/__main__.py
LingzuWenkuFix1/file.epub
LingzuWenkuFix1/index.html
LingzuWenkuFix1/css/__init__.py
LingzuWenkuFix1/css/annotations.css
LingzuWenkuFix1/css/main.css
LingzuWenkuFix1/css/normalize.css
LingzuWenkuFix1/css/popup.css
LingzuWenkuFix1/font/__init__.py
LingzuWenkuFix1/font/fontello.eot
LingzuWenkuFix1/font/fontello.svg
LingzuWenkuFix1/font/fontello.ttf
LingzuWenkuFix1/font/fontello.woff
LingzuWenkuFix1/img/__init__.py
LingzuWenkuFix1/img/annotator-glyph-sprite.png
LingzuWenkuFix1/img/annotator-icon-sprite.png
LingzuWenkuFix1/img/apple-touch-icon.png
LingzuWenkuFix1/img/cancelfullscreen.png
LingzuWenkuFix1/img/close.png
LingzuWenkuFix1/img/fullscreen.png
LingzuWenkuFix1/img/loader.gif
LingzuWenkuFix1/img/menu-icon.png
LingzuWenkuFix1/img/save.png
LingzuWenkuFix1/img/saved.png
LingzuWenkuFix1/img/settings-s.png
LingzuWenkuFix1/img/settings.png
LingzuWenkuFix1/img/star.png
LingzuWenkuFix1/js/__init__.py
LingzuWenkuFix1/js/epub.js
LingzuWenkuFix1/js/epub.min.js
LingzuWenkuFix1/js/epub.min.map
LingzuWenkuFix1/js/hooks.min.js
LingzuWenkuFix1/js/hooks.min.map
LingzuWenkuFix1/js/reader.js
LingzuWenkuFix1/js/reader.js.map
LingzuWenkuFix1/js/reader.min.js
LingzuWenkuFix1/js/reader.min.map
LingzuWenkuFix1/js/hooks/__init__.py
LingzuWenkuFix1/js/hooks/extensions/__init__.py
LingzuWenkuFix1/js/hooks/extensions/highlight.js
LingzuWenkuFix1/js/libs/__init__.py
LingzuWenkuFix1/js/libs/jquery.min.js
LingzuWenkuFix1/js/libs/localforage.min.js
LingzuWenkuFix1/js/libs/screenfull.js
LingzuWenkuFix1/js/libs/screenfull.min.js
LingzuWenkuFix1/js/libs/zip.min.js
LingzuWenkuFix1/js/plugins/__init__.py
LingzuWenkuFix1/js/plugins/hypothesis.js
LingzuWenkuFix1/js/plugins/search.js
lingzu_wenku_fix1-2025.3.25.0.dist-info/METADATA
lingzu_wenku_fix1-2025.3.25.0.dist-info/WHEEL
lingzu_wenku_fix1-2025.3.25.0.dist-info/entry_points.txt
lingzu_wenku_fix1-2025.3.25.0.dist-info/top_level.txt
lingzu_wenku_fix1-2025.3.25.0.dist-info/RECORD
